{
  "forms": [
    {
      "name": "form1",
      "components": [
        {
          "name": "firstname",
          "title": "First Name",
          "help": "Enter your first name",
          "type": "textfield",
          "required": true
        },
        {
          "name": "lastname",
          "title": "Last Name",
          "help": "Enter your last name",
          "type": "textfield",
          "required": true
        }
      ],
      "title": "Name",
      "layout": "vertical",
      "type": "form"
    },
    {
      "name": "form2",
      "components": [
        {
          "name": "companyname",
          "title": "Company Name",
          "help": "Name of the company you work for",
          "type": "textfield",
          "required": true
        },
        {
          "name": "jobposition",
          "title": "Job Position",
          "help": "Your current job position",
          "type": "textfield",
          "required": true
        }
      ],
      "title": "Job Position",
      "layout": "vertical",
      "type": "form"
    }
  ],
  "layout": "vertical",
  "title": "Job Survey",
  "name": "formBoxExample",
  "type": "formbox"
}
